{
  "openapi": "3.0.3",
  "info": {
    "title": "Ideas Banking",
    "description": "This documentation has been automatically generated by Treblle. Visit https://treblle.com/ and get started for FREE.",
    "version": "1.0.0"
  },
  "servers": [
    {
      "url": "https://localhost:3000"
    }
  ],
  "paths": {
    "/api/transactions": {
      "post": {
        "operationId": "3721b1b1-38c3-45b5-bc29-edbfacc7efed",
        "tags": [
          "api"
        ],
        "requestBody": {
          "required": true,
          "content": {
            "application/x-www-form-urlencoded": {
              "schema": {
                "type": "object",
                "properties": {
                  "monto": {
                    "type": "number"
                  },
                  "origen_usuario_id": {
                    "type": "integer"
                  },
                  "tarjeta_origen": {
                    "type": "string"
                  },
                  "tarjeta_destino": {
                    "type": "string"
                  }
                }
              }
            }
          }
        },
        "description":"Registra una transaccion y actualiza el saldo de los usuarios.",
        "responses": {
          "200": {
            "description": "POST /api/transactions",
            "content": {
              "application/json": {
                "schema": {
                  "type": "object",
                  "properties": {
                    "message": {
                      "type": "string"
                    }
                  }
                }
              }
            }
          }
        }
      },
      "get": {
        "operationId": "19d74d3b-c861-432a-b869-ad708563adc1",
        "tags": [
          "api"
        ],
        "parameters": [
          {
            "name": "id",
            "in": "query",
            "required": false,
            "schema": {
              "type": "string"
            }
          }
        ],
        "description":"Devuelve todas las transacciones de un usuario.",
        "responses": {
          "200": {
            "description": "GET /api/transactions",
            "content": {
              "application/json": {
                "schema": {
                  "type": "array",
                  "items": {
                    "type": "object",
                    "properties": {
                      "id": {
                        "type": "string"
                      },
                      "monto": {
                        "type": "string"
                      },
                      "origen_usuario_id": {
                        "type": "integer"
                      },
                      "tarjeta_origen": {
                        "type": "string"
                      },
                      "destino_usuario_id": {
                        "type": "integer"
                      },
                      "tarjeta_destino": {
                        "type": "string"
                      }
                    }
                  }
                }
              }
            }
          }
        }
      }
    },
    "/api/users": {
      "post": {
        "operationId": "5e8d2802-4156-476b-8129-fc34ef54e8ca",
        "tags": [
          "api"
        ],
        "requestBody": {
          "required": true,
          "content": {
            "application/x-www-form-urlencoded": {
              "schema": {
                "type": "object",
                "properties": {
                  "nombre": {
                    "type": "string"
                  },
                  "apellido": {
                    "type": "string"
                  },
                  "pin": {
                    "type": "string"
                  },
                  "saldo": {
                    "type": "number"
                  }
                }
              }
            }
          }
        },
        "description":"Registra un nuevo usuario (mas alla del alcance del proyecto).",
        "responses": {
          "200": {
            "description": "POST /api/users",
            "content": {
              "application/json": {
                "schema": {
                  "type": "object",
                  "properties": {
                    "message": {
                      "type": "string"
                    }
                  }
                }
              }
            }
          }
        }
      }
    }
  }
}